livox_sdk.cpython-38-x86_64-linux-gnu.so
py_livox2-0.0.2.dist-info/WHEEL
py_livox2-0.0.2.dist-info/entry_points.txt
py_livox2-0.0.2.dist-info/METADATA
py_livox2-0.0.2.dist-info/RECORD
py_livox2-0.0.2.dist-info/licenses/LICENSE.txt
lib/liblivox_lidar_sdk_static.a
lib/liblivox_lidar_sdk_shared.so
livox_sdk_cli/__init__.py
livox_sdk_cli/cli/livox_runner.py
livox_sdk_cli/cli/entry.py
livox_sdk_cli/cli/config_store.py
livox_sdk_cli/cli/__init__.py
livox_sdk_cli/cli/config_cli.py
livox_sdk_cli/cfg/schema.py
livox_sdk_cli/cfg/__init__.py
livox_sdk_cli/cfg/livox_start.yaml
livox_sdk_cli/ivox2/iceoryx_bridge.py
livox_sdk_cli/ivox2/test_pointcloud_publisher.py
livox_sdk_cli/ivox2/iceoryx_msgs.py
livox_sdk_cli/ivox2/__init__.py
include/livox_lidar_api.h
include/livox_lidar_cfg.h
include/livox_lidar_def.h
