Metadata-Version: 2.1
Name: py-livox2
Version: 0.0.2
Summary: Python bindings for the Livox SDK2 with a ready-to-run CLI demo.
Author-Email: Astrorix <astrorix@hotmail.com>
License: The following portions of the LIVOX’s Livox SDK2 (“Software” referred to in the terms below) are made available to you under the terms of the MIT License. A copy of the MIT license is provided below and is also available at https://opensource.org/licenses/MIT.
Classifier: Programming Language :: Python :: 3
Classifier: Programming Language :: Python :: 3.8
Classifier: Programming Language :: Python :: 3.9
Classifier: Programming Language :: Python :: 3.10
Classifier: Programming Language :: Python :: 3.11
Classifier: Programming Language :: Python :: 3.12
Classifier: Operating System :: POSIX :: Linux
Classifier: License :: OSI Approved :: MIT License
Requires-Python: >=3.8
Requires-Dist: numpy>=1.20
Requires-Dist: PyYAML>=6.0
Provides-Extra: dev
Requires-Dist: build; extra == "dev"
Requires-Dist: ruff; extra == "dev"
Provides-Extra: ipc
Requires-Dist: iceoryx2>=0.7; extra == "ipc"
